<encounterParticipant typeCode="ATND">
  <templateId root="2.16.840.1.113883.10.20.6.2.2" extension="2014-06-09" />
  <assignedEntity>
    <id extension="44444444" root="2.16.840.1.113883.4.6" />
    <code code="208D00000X" codeSystem="2.16.840.1.113883.6.101" codeSystemName="NUCC" displayName="General Practice" />
    <addr nullFlavor="NI" />
    <telecom nullFlavor="NI" />
    <assignedPerson>
      <name>
        <prefix>Dr.</prefix>
        <given>Fay</given>
        <family>Family</family>
      </name>
    </assignedPerson>
  </assignedEntity>
</encounterParticipant>